mas_test0001.py
mas_test0001-0.1.0.dist-info/METADATA
mas_test0001-0.1.0.dist-info/WHEEL
mas_test0001-0.1.0.dist-info/entry_points.txt
mas_test0001-0.1.0.dist-info/top_level.txt
mas_test0001-0.1.0.dist-info/RECORD
