Metadata-Version: 2.4
Name: mas_test0001
Version: 0.1.0
Summary: Add your description here
Requires-Python: >=3.12
Requires-Dist: matplotlib>=3.10.6
Requires-Dist: numpy>=2.3.3
Requires-Dist: scipy>=1.16.2
